gfw/__init__.py
gfw/datasets.json
gfw/gfw.py
gfw-0.0.4.dist-info/LICENSE
gfw-0.0.4.dist-info/METADATA
gfw-0.0.4.dist-info/WHEEL
gfw-0.0.4.dist-info/entry_points.txt
gfw-0.0.4.dist-info/top_level.txt
gfw-0.0.4.dist-info/RECORD
