Metadata-Version: 2.1
Name: gfw
Version: 0.0.4
Summary: Simple CLI for Global Fishing Watch Data
Home-page: https://github.com/samapriya/gfw
Author: Samapriya Roy
Author-email: samapriya.roy@gmail.com
License: Apache 2.0
Platform: UNKNOWN
Classifier: Intended Audience :: Developers
Classifier: Intended Audience :: Science/Research
Classifier: Natural Language :: English
Classifier: License :: OSI Approved :: Apache Software License
Classifier: Programming Language :: Python :: 3.6
Classifier: Programming Language :: Python :: 3.7
Classifier: Operating System :: OS Independent
Classifier: Topic :: Scientific/Engineering :: GIS
Requires-Dist: requests (>=2.26.0)
Requires-Dist: tenacity (>=8.0.1)
Requires-Dist: beautifulsoup4 (>=4.10.0)
Requires-Dist: tabulate (>=0.8.9)
